Workbook

Sheet Asset Data_Initial Contract
A1: Month of Period Start | B1: Machine ID:SERIAL # | C1: Sum of Coin In | D1: Sum of Net Win | E1: Net Win_2 (Players Reward deducted) | F1: EGM Day Count | G1: WPUPD | H1: Fee/Revenue | I1: Distinct Ser# Count | J1: Revenue Share | K1: ='Fee Initial Contract'!F18 -> 0.14123422 | M1: OPAP's Players Reward Scheme cost | N1: 3769.7781 | O1: OPAP's Players Reward Scheme cost per machine | P1: =N1/I5731 -> 0.65801677
A2: 45962 | B2: 2253017 | C2: 4578 | D2: 496.37 | E2: =D2-$P$1 -> 495.71198 | F2: 30 | G2: =D2/F2 -> 16.545667 | H2: =E2*$K$1 -> 70.011494 | I2: 1
A3: 45962 | B3: 2253103 | C3: 18328 | D3: 1005.18 | E3: =D3-$P$1 -> 1004.522 | F3: 30 | G3: =D3/F3 -> 33.506 | H3: =E3*$K$1 -> 141.87288 | I3: 1
A4: 45962 | B4: 2253112 | C4: 1855 | D4: 286.36 | E4: =D4-$P$1 -> 285.70198 | F4: 6 | G4: =D4/F4 -> 47.726667 | H4: =E4*$K$1 -> 40.350896 | I4: 1
A5: 45962 | B5: 2253118 | C5: 5071 | D5: -22.79 | E5: =D5-$P$1 -> -23.448017 | F5: 30 | G5: =D5/F5 -> -0.75966667 | H5: =E5*$K$1 -> -3.3116623 | I5: 1
A6: 45962 | B6: 2253119 | C6: 2965 | D6: -401.75 | E6: =D6-$P$1 -> -402.40802 | F6: 30 | G6: =D6/F6 -> -13.391667 | H6: =E6*$K$1 -> -56.833782 | I6: 1
A7: 45962 | B7: 2377541 | C7: 2811 | D7: 216.25 | E7: =D7-$P$1 -> 215.59198 | F7: 30 | G7: =D7/F7 -> 7.2083333 | H7: =E7*$K$1 -> 30.448965 | I7: 1
A8: 45962 | B8: 2377544 | C8: 1063 | D8: 119.95 | E8: =D8-$P$1 -> 119.29198 | F8: 30 | G8: =D8/F8 -> 3.9983333 | H8: =E8*$K$1 -> 16.84811 | I8: 1
A9: 45962 | B9: 2377547 | C9: 646 | D9: -66.04 | E9: =D9-$P$1 -> -66.698017 | F9: 17 | G9: =D9/F9 -> -3.8847059 | H9: =E9*$K$1 -> -9.4200423 | I9: 1
A10: 45962 | B10: 2377554 | C10: 1418 | D10: 173.68 | E10: =D10-$P$1 -> 173.02198 | F10: 25 | G10: =D10/F10 -> 6.9472 | H10: =E10*$K$1 -> 24.436625 | I10: 1
A11: 45962 | B11: 2377555 | C11: 294 | D11: -6.82 | E11: =D11-$P$1 -> -7.4780168 | F11: 26 | G11: =D11/F11 -> -0.26230769 | H11: =E11*$K$1 -> -1.0561519 | I11: 1
A12: 45962 | B12: 2377556 | C12: 378 | D12: -309.12 | E12: =D12-$P$1 -> -309.77802 | F12: 30 | G12: =D12/F12 -> -10.304 | H12: =E12*$K$1 -> -43.751256 | I12: 1
A13: 45962 | B13: 2377557 | C13: 2493 | D13: -391.12 | E13: =D13-$P$1 -> -391.77802 | F13: 25 | G13: =D13/F13 -> -15.6448 | H13: =E13*$K$1 -> -55.332462 | I13: 1
A14: 45962 | B14: 2377561 | C14: 0 | E14: =D14-$P$1 -> -0.65801677 | F14: 30 | G14: =D14/F14 -> 0 | H14: =E14*$K$1 -> -0.092934485 | I14: 1
A15: 45962 | B15: 2377562 | C15: 10828 | D15: 174.48 | E15: =D15-$P$1 -> 173.82198 | F15: 30 | G15: =D15/F15 -> 5.816 | H15: =E15*$K$1 -> 24.549612 | I15: 1
A16: 45962 | B16: 2377567 | C16: 12516 | D16: 1991.69 | E16: =D16-$P$1 -> 1991.032 | F16: 30 | G16: =D16/F16 -> 66.389667 | H16: =E16*$K$1 -> 281.20185 | I16: 1
A17: 45962 | B17: 2377573 | C17: 14695 | D17: 416.78 | E17: =D17-$P$1 -> 416.12198 | F17: 30 | G17: =D17/F17 -> 13.892667 | H17: =E17*$K$1 -> 58.770663 | I17: 1
A18: 45962 | B18: 2377575 | C18: 2269 | D18: 521.2 | E18: =D18-$P$1 -> 520.54198 | F18: 17 | G18: =D18/F18 -> 30.658824 | H18: =E18*$K$1 -> 73.51834 | I18: 1
A19: 45962 | B19: 2377579 | C19: 209 | D19: 99.48 | E19: =D19-$P$1 -> 98.821983 | F19: 12 | G19: =D19/F19 -> 8.29 | H19: =E19*$K$1 -> 13.957046 | I19: 1
A20: 45962 | B20: 2377582 | C20: 11817 | D20: 8.62 | E20: =D20-$P$1 -> 7.9619832 | F20: 30 | G20: =D20/F20 -> 0.28733333 | H20: =E20*$K$1 -> 1.1245045 | I20: 1
A21: 45962 | B21: 2377593 | C21: 121 | D21: 36.13 | E21: =D21-$P$1 -> 35.471983 | F21: 30 | G21: =D21/F21 -> 1.2043333 | H21: =E21*$K$1 -> 5.0098578 | I21: 1
A22: 45962 | B22: 2377612 | C22: 0 | E22: =D22-$P$1 -> -0.65801677 | F22: 7 | G22: =D22/F22 -> 0 | H22: =E22*$K$1 -> -0.092934485 | I22: 1
A23: 45962 | B23: 2377631 | C23: 1079 | D23: -140.1 | E23: =D23-$P$1 -> -140.75802 | F23: 17 | G23: =D23/F23 -> -8.2411765 | H23: =E23*$K$1 -> -19.879848 | I23: 1
A24: 45962 | B24: 2377633 | C24: 221 | D24: 93.94 | E24: =D24-$P$1 -> 93.281983 | F24: 17 | G24: =D24/F24 -> 5.5258824 | H24: =E24*$K$1 -> 13.174608 | I24: 1
A25: 45962 | B25: 2377636 | C25: 3195 | D25: 459.02 | E25: =D25-$P$1 -> 458.36198 | F25: 13 | G25: =D25/F25 -> 35.309231 | H25: =E25*$K$1 -> 64.736396 | I25: 1
A26: 45962 | B26: 2377648 | C26: 1656 | D26: 292.04 | E26: =D26-$P$1 -> 291.38198 | F26: 29 | G26: =D26/F26 -> 10.070345 | H26: =E26*$K$1 -> 41.153107 | I26: 1
A27: 45962 | B27: 2377655 | C27: 1241 | D27: 188.26 | E27: =D27-$P$1 -> 187.60198 | F27: 24 | G27: =D27/F27 -> 7.8441667 | H27: =E27*$K$1 -> 26.495819 | I27: 1
A28: 45962 | B28: 2377658 | C28: 0 | E28: =D28-$P$1 -> -0.65801677 | F28: 29 | G28: =D28/F28 -> 0 | H28: =E28*$K$1 -> -0.092934485 | I28: 1
A29: 45962 | B29: 2378193 | C29: 0 | E29: =D29-$P$1 -> -0.65801677 | F29: 3 | G29: =D29/F29 -> 0 | H29: =E29*$K$1 -> -0.092934485 | I29: 1
A30: 45962 | B30: 2378205 | C30: 2820 | D30: 576.56 | E30: =D30-$P$1 -> 575.90198 | F30: 19 | G30: =D30/F30 -> 30.345263 | H30: =E30*$K$1 -> 81.337066 | I30: 1
A31: 45962 | B31: 2378206 | C31: 3675 | D31: 677.81 | E31: =D31-$P$1 -> 677.15198 | F31: 30 | G31: =D31/F31 -> 22.593667 | H31: =E31*$K$1 -> 95.637031 | I31: 1
A32: 45962 | B32: 2378210 | C32: 319 | D32: -14.07 | E32: =D32-$P$1 -> -14.728017 | F32: 30 | G32: =D32/F32 -> -0.469 | H32: =E32*$K$1 -> -2.0800999 | I32: 1
A33: 45962 | B33: 2378215 | C33: 196 | D33: 4.43 | E33: =D33-$P$1 -> 3.7719832 | F33: 5 | G33: =D33/F33 -> 0.886 | H33: =E33*$K$1 -> 0.5327331 | I33: 1
A34: 45962 | B34: 2378216 | C34: 6754 | D34: 1083.95 | E34: =D34-$P$1 -> 1083.292 | F34: 30 | G34: =D34/F34 -> 36.131667 | H34: =E34*$K$1 -> 152.9979 | I34: 1
A35: 45962 | B35: 2378244 | C35: 0 | E35: =D35-$P$1 -> -0.65801677 | F35: 30 | G35: =D35/F35 -> 0 | H35: =E35*$K$1 -> -0.092934485 | I35: 1
A36: 45962 | B36: 2378248 | C36: 6549 | D36: 702.3 | E36: =D36-$P$1 -> 701.64198 | F36: 30 | G36: =D36/F36 -> 23.41 | H36: =E36*$K$1 -> 99.095857 | I36: 1
A37: 45962 | B37: 2378249 | C37: 640 | D37: 102.76 | E37: =D37-$P$1 -> 102.10198 | F37: 10 | G37: =D37/F37 -> 10.276 | H37: =E37*$K$1 -> 14.420294 | I37: 1
A38: 45962 | B38: 2378252 | C38: 1068 | D38: 173.17 | E38: =D38-$P$1 -> 172.51198 | F38: 30 | G38: =D38/F38 -> 5.7723333 | H38: =E38*$K$1 -> 24.364595 | I38: 1
A39: 45962 | B39: 2378253 | C39: 21266 | D39: 2005.47 | E39: =D39-$P$1 -> 2004.812 | F39: 22 | G39: =D39/F39 -> 91.157727 | H39: =E39*$K$1 -> 283.14805 | I39: 1
A40: 45962 | B40: 2378254 | C40: 2326 | D40: 392.98 | E40: =D40-$P$1 -> 392.32198 | F40: 30 | G40: =D40/F40 -> 13.099333 | H40: =E40*$K$1 -> 55.409289 | I40: 1
A41: 45962 | B41: 2378259 | C41: 1497 | D41: -348.44 | E41: =D41-$P$1 -> -349.09802 | F41: 30 | G41: =D41/F41 -> -11.614667 | H41: =E41*$K$1 -> -49.304586 | I41: 1
A42: 45962 | B42: 2378265 | C42: 1330 | D42: 341.96 | E42: =D42-$P$1 -> 341.30198 | F42: 30 | G42: =D42/F42 -> 11.398667 | H42: =E42*$K$1 -> 48.203519 | I42: 1
A43: 45962 | B43: 2378276 | C43: 1010 | D43: -449.08 | E43: =D43-$P$1 -> -449.73802 | F43: 30 | G43: =D43/F43 -> -14.969333 | H43: =E43*$K$1 -> -63.518397 | I43: 1
A44: 45962 | B44: 2378277 | C44: 0 | E44: =D44-$P$1 -> -0.65801677 | F44: 19 | G44: =D44/F44 -> 0 | H44: =E44*$K$1 -> -0.092934485 | I44: 1
A45: 45962 | B45: 2378279 | C45: 167 | D45: 40.2 | E45: =D45-$P$1 -> 39.541983 | F45: 30 | G45: =D45/F45 -> 1.34 | H45: =E45*$K$1 -> 5.5846811 | I45: 1
A46: 45962 | B46: 2378280 | C46: 922 | D46: 35.68 | E46: =D46-$P$1 -> 35.021983 | F46: 30 | G46: =D46/F46 -> 1.1893333 | H46: =E46*$K$1 -> 4.9463024 | I46: 1
A47: 45962 | B47: 2378282 | C47: 1701 | D47: 127.44 | E47: =D47-$P$1 -> 126.78198 | F47: 30 | G47: =D47/F47 -> 4.248 | H47: =E47*$K$1 -> 17.905954 | I47: 1
A48: 45962 | B48: 2378285 | C48: 1116 | D48: 284.1 | E48: =D48-$P$1 -> 283.44198 | F48: 18 | G48: =D48/F48 -> 15.783333 | H48: =E48*$K$1 -> 40.031707 | I48: 1
A49: 45962 | B49: 2378289 | C49: 127 | D49: -46.28 | E49: =D49-$P$1 -> -46.938017 | F49: 30 | G49: =D49/F49 -> -1.5426667 | H49: =E49*$K$1 -> -6.6292541 | I49: 1
A50: 45962 | B50: 2378293 | C50: 420 | D50: -49.72 | E50: =D50-$P$1 -> -50.378017 | F50: 30 | G50: =D50/F50 -> -1.6573333 | H50: =E50*$K$1 -> -7.1150998 | I50: 1
A51: 45962 | B51: 2378297 | C51: 5516 | D51: 797.2 | E51: =D51-$P$1 -> 796.54198 | F51: 30 | G51: =D51/F51 -> 26.573333 | H51: =E51*$K$1 -> 112.49898 | I51: 1
A52: 45962 | B52: 2378299 | C52: 276 | D52: 55.03 | E52: =D52-$P$1 -> 54.371983 | F52: 30 | G52: =D52/F52 -> 1.8343333 | H52: =E52*$K$1 -> 7.6791845 | I52: 1
A53: 45962 | B53: 2378307 | C53: 59 | D53: 7.97 | E53: =D53-$P$1 -> 7.3119832 | F53: 30 | G53: =D53/F53 -> 0.26566667 | H53: =E53*$K$1 -> 1.0327022 | I53: 1
A54: 45962 | B54: 2378315 | C54: 16880 | D54: 1532.72 | E54: =D54-$P$1 -> 1532.062 | F54: 30 | G54: =D54/F54 -> 51.090667 | H54: =E54*$K$1 -> 216.37958 | I54: 1
A55: 45962 | B55: 2379394 | C55: 4036 | D55: 563.85 | E55: =D55-$P$1 -> 563.19198 | F55: 1 | G55: =D55/F55 -> 563.85 | H55: =E55*$K$1 -> 79.541979 | I55: 1
A56: 45962 | B56: 2379397 | C56: 601 | D56: 23.96 | E56: =D56-$P$1 -> 23.301983 | F56: 30 | G56: =D56/F56 -> 0.79866667 | H56: =E56*$K$1 -> 3.2910374 | I56: 1
... A62: 45962 | B62: 2379421 | C62: 2733 | D62: -305.56 | E62: =D62-$P$1 -> -306.21802 | F62: 30 | G62: =D62/F62 -> -10.185333 | H62: =E62*$K$1 -> -43.248462 | I62: 1
A63: 45962 | B63: 2379422 | C63: 0 | E63: =D63-$P$1 -> -0.65801677 | F63: 30 | G63: =D63/F63 -> 0 | H63: =E63*$K$1 -> -0.092934485 | I63: 1
A64: 45962 | B64: 2379425 | C64: 27350 | D64: 1005.78 | E64: =D64-$P$1 -> 1005.122 | F64: 30 | G64: =D64/F64 -> 33.526 | H64: =E64*$K$1 -> 141.95762 | I64: 1
A65: 45962 | B65: 2379435 | C65: 118 | D65: 39.82 | E65: =D65-$P$1 -> 39.161983 | F65: 30 | G65: =D65/F65 -> 1.3273333 | H65: =E65*$K$1 -> 5.5310121 | I65: 1
A66: 45962 | B66: 2379436 | C66: 2936 | D66: 217.88 | E66: =D66-$P$1 -> 217.22198 | F66: 20 | G66: =D66/F66 -> 10.894 | H66: =E66*$K$1 -> 30.679177 | I66: 1
A67: 45962 | B67: 2379438 | C67: 5939 | D67: 652.96 | E67: =D67-$P$1 -> 652.30198 | F67: 30 | G67: =D67/F67 -> 21.765333 | H67: =E67*$K$1 -> 92.127361 | I67: 1
A68: 45962 | B68: 2379444 | C68: 153 | D68: -0.35 | E68: =D68-$P$1 -> -1.0080168 | F68: 12 | G68: =D68/F68 -> -0.029166667 | H68: =E68*$K$1 -> -0.14236646 | I68: 1
A69: 45962 | B69: 2379451 | C69: 44857 | D69: 4495.48 | E69: =D69-$P$1 -> 4494.822 | F69: 30 | G69: =D69/F69 -> 149.84933 | H69: =E69*$K$1 -> 634.82267 | I69: 1
A70: 45962 | B70: 2379463 | C70: 8674 | D70: 370.52 | E70: =D70-$P$1 -> 369.86198 | F70: 30 | G70: =D70/F70 -> 12.350667 | H70: =E70*$K$1 -> 52.237168 | I70: 1
A71: 45962 | B71: 2379467 | C71: 513 | D71: 71.78 | E71: =D71-$P$1 -> 71.121983 | F71: 25 | G71: =D71/F71 -> 2.8712 | H71: =E71*$K$1 -> 10.044858 | I71: 1
A72: 45962 | B72: 2379469 | C72: 104 | D72: 49.79 | E72: =D72-$P$1 -> 49.131983 | F72: 24 | G72: =D72/F72 -> 2.0745833 | H72: =E72*$K$1 -> 6.9391172 | I72: 1
A73: 45962 | B73: 2379476 | C73: 10840 | D73: 684.94 | E73: =D73-$P$1 -> 684.28198 | F73: 30 | G73: =D73/F73 -> 22.831333 | H73: =E73*$K$1 -> 96.644031 | I73: 1
A74: 45962 | B74: 2379489 | C74: 124 | D74: 37.17 | E74: =D74-$P$1 -> 36.511983 | F74: 17 | G74: =D74/F74 -> 2.1864706 | H74: =E74*$K$1 -> 5.1567414 | I74: 1
A75: 45962 | B75: 2379497 | C75: 18264 | D75: -456.69 | E75: =D75-$P$1 -> -457.34802 | F75: 30 | G75: =D75/F75 -> -15.223 | H75: =E75*$K$1 -> -64.59319 | I75: 1
... A78: 45962 | B78: 2379508 | C78: 31930 | D78: 4148.98 | E78: =D78-$P$1 -> 4148.322 | F78: 30 | G78: =D78/F78 -> 138.29933 | H78: =E78*$K$1 -> 585.88501 | I78: 1
A79: 45962 | B79: 2379514 | C79: 0 | E79: =D79-$P$1 -> -0.65801677 | F79: 30 | G79: =D79/F79 -> 0 | H79: =E79*$K$1 -> -0.092934485 | I79: 1
A80: 45962 | B80: 2379524 | C80: 2088 | D80: 271.5 | E80: =D80-$P$1 -> 270.84198 | F80: 30 | G80: =D80/F80 -> 9.05 | H80: =E80*$K$1 -> 38.252156 | I80: 1
A81: 45962 | B81: 2379527 | C81: 1440 | D81: 188.83 | E81: =D81-$P$1 -> 188.17198 | F81: 18 | G81: =D81/F81 -> 10.490556 | H81: =E81*$K$1 -> 26.576323 | I81: 1
A82: 45962 | B82: 2379532 | C82: 543 | D82: 224.74 | E82: =D82-$P$1 -> 224.08198 | F82: 30 | G82: =D82/F82 -> 7.4913333 | H82: =E82*$K$1 -> 31.648044 | I82: 1
A83: 45962 | B83: 2379537 | C83: 0 | E83: =D83-$P$1 -> -0.65801677 | F83: 30 | G83: =D83/F83 -> 0 | H83: =E83*$K$1 -> -0.092934485 | I83: 1
A84: 45962 | B84: 2379544 | C84: 11699 | D84: 1042.94 | E84: =D84-$P$1 -> 1042.282 | F84: 30 | G84: =D84/F84 -> 34.764667 | H84: =E84*$K$1 -> 147.20588 | I84: 1
A85: 45962 | B85: 2379548 | C85: 8220 | D85: 1256.27 | E85: =D85-$P$1 -> 1255.612 | F85: 30 | G85: =D85/F85 -> 41.875667 | H85: =E85*$K$1 -> 177.33538 | I85: 1
A86: 45962 | B86: 2379551 | C86: 59 | D86: -4.94 | E86: =D86-$P$1 -> -5.5980168 | F86: 30 | G86: =D86/F86 -> -0.16466667 | H86: =E86*$K$1 -> -0.79063152 | I86: 1
A87: 45962 | B87: 2379553 | C87: 15014 | D87: 2029.14 | E87: =D87-$P$1 -> 2028.482 | F87: 30 | G87: =D87/F87 -> 67.638 | H87: =E87*$K$1 -> 286.49107 | I87: 1
A88: 45962 | B88: 2379555 | C88: 6819 | D88: 465.61 | E88: =D88-$P$1 -> 464.95198 | F88: 30 | G88: =D88/F88 -> 15.520333 | H88: =E88*$K$1 -> 65.66713 | I88: 1
A89: 45962 | B89: 2379565 | C89: 8592 | D89: -212.6 | E89: =D89-$P$1 -> -213.25802 | F89: 30 | G89: =D89/F89 -> -7.0866667 | H89: =E89*$K$1 -> -30.119329 | I89: 1
A90: 45962 | B90: 2379573 | C90: 9535 | D90: 574.28 | E90: =D90-$P$1 -> 573.62198 | F90: 30 | G90: =D90/F90 -> 19.142667 | H90: =E90*$K$1 -> 81.015052 | I90: 1
A91: 45962 | B91: 2387013 | C91: 27784 | D91: 1874.41 | E91: =D91-$P$1 -> 1873.752 | F91: 30 | G91: =D91/F91 -> 62.480333 | H91: =E91*$K$1 -> 264.6379 | I91: 1
A92: 45962 | B92: 2387020 | C92: 6036 | D92: 873.99 | E92: =D92-$P$1 -> 873.33198 | F92: 30 | G92: =D92/F92 -> 29.133 | H92: =E92*$K$1 -> 123.34436 | I92: 1
A93: 45962 | B93: 2387048 | C93: 5313 | D93: 291.22 | E93: =D93-$P$1 -> 290.56198 | F93: 30 | G93: =D93/F93 -> 9.7073333 | H93: =E93*$K$1 -> 41.037295 | I93: 1
A94: 45962 | B94: 2387083 | C94: 2710 | D94: 240.4 | E94: =D94-$P$1 -> 239.74198 | F94: 30 | G94: =D94/F94 -> 8.0133333 | H94: =E94*$K$1 -> 33.859772 | I94: 1
A95: 45962 | B95: 2387084 | C95: 3301 | D95: 365.6 | E95: =D95-$P$1 -> 364.94198 | F95: 30 | G95: =D95/F95 -> 12.186667 | H95: =E95*$K$1 -> 51.542296 | I95: 1
... A118: 45962 | B118: 2388578 | C118: 1065 | D118: 269.65 | E118: =D118-$P$1 -> 268.99198 | F118: 30 | G118: =D118/F118 -> 8.9883333 | H118: =E118*$K$1 -> 37.990872 | I118: 1
A119: 45962 | B119: 2389253 | C119: 0 | E119: =D119-$P$1 -> -0.65801677 | F119: 1 | G119: =D119/F119 -> 0 | H119: =E119*$K$1 -> -0.092934485 | I119: 1
A120: 45962 | B120: 2389256 | C120: 20327 | D120: -252.01 | E120: =D120-$P$1 -> -252.66802 | F120: 30 | G120: =D120/F120 -> -8.4003333 | H120: =E120*$K$1 -> -35.68537 | I120: 1
A121: 45962 | B121: 2389258 | C121: 4656 | D121: 757.44 | E121: =D121-$P$1 -> 756.78198 | F121: 30 | G121: =D121/F121 -> 25.248 | H121: =E121*$K$1 -> 106.88351 | I121: 1
A122: 45962 | B122: 2389267 | C122: 4403 | D122: 819.79 | E122: =D122-$P$1 -> 819.13198 | F122: 28 | G122: =D122/F122 -> 29.278214 | H122: =E122*$K$1 -> 115.68947 | I122: 1
A123: 45962 | B123: 2389294 | C123: 7470 | D123: -172.11 | E123: =D123-$P$1 -> -172.76802 | F123: 30 | G123: =D123/F123 -> -5.737 | H123: =E123*$K$1 -> -24.400756 | I123: 1
A124: 45962 | B124: 2389297 | C124: 0 | E124: =D124-$P$1 -> -0.65801677 | F124: 30 | G124: =D124/F124 -> 0 | H124: =E124*$K$1 -> -0.092934485 | I124: 1
A125: 45962 | B125: 2389299 | C125: 281 | D125: 50.55 | E125: =D125-$P$1 -> 49.891983 | F125: 30 | G125: =D125/F125 -> 1.685 | H125: =E125*$K$1 -> 7.0464552 | I125: 1
A126: 45962 | B126: 2389303 | C126: 23509 | D126: 2534.9 | E126: =D126-$P$1 -> 2534.242 | F126: 30 | G126: =D126/F126 -> 84.496667 | H126: =E126*$K$1 -> 357.92169 | I126: 1
A127: 45962 | B127: 2389309 | C127: 9126 | D127: 1036.36 | E127: =D127-$P$1 -> 1035.702 | F127: 25 | G127: =D127/F127 -> 41.4544 | H127: =E127*$K$1 -> 146.27656 | I127: 1
A128: 45962 | B128: 2389310 | C128: 7500 | D128: 1009.69 | E128: =D128-$P$1 -> 1009.032 | F128: 30 | G128: =D128/F128 -> 33.656333 | H128: =E128*$K$1 -> 142.50984 | I128: 1
A129: 45962 | B129: 2389700 | C129: 2 | D129: 1.55 | E129: =D129-$P$1 -> 0.89198323 | F129: 29 | G129: =D129/F129 -> 0.053448276 | H129: =E129*$K$1 -> 0.12597855 | I129: 1
...

Sheet Fee Initial Contract
A1: Sum of Daily NGR of all VLTs for a month period (invoice period): | F1: =L1*0.7 -> 5848405 | K1: GGR | L1: ='Asset Data_Initial Contract'!E5731 -> 8354864.3
A2: Sum of operational days (reported days) of all VLTs for a month period: | F2: ='Asset Data_Initial Contract'!F5731 -> 164345 | K2: WPUPD | L2: =F3/0.7 -> 50.83735
A3: Average NGR per day per VLT for a month period : | F3: =F1/F2 -> 35.586145 | G3: NWPUPD
A5: OPERATING FEE CALCULATION
A6: Scale | C6: % Commision | D6: Avr/NGR/month | E6: OP days | F6: Fee
D7: =F3 -> 35.586145
A8: 0 | B8: 28.99 | C8: 0.217 | D8: =MIN(D7,B8) -> 28.99 | E8: =F2 -> 164345 | F8: =D8*E8*C8 -> 1033866.5
A9: 29 | B9: 34.99 | C9: 0.139 | D9: =MIN((D7-D8),(B9-B8)) -> 6 | E9: =F2 -> 164345 | F9: =D9*E9*C9 -> 137063.73
A10: 35 | B10: 42.99 | C10: 0.0925 | D10: =MIN((D7-D8-D9),(B10-B9)) -> 0.59614524 | E10: =F2 -> 164345 | F10: =D10*E10*C10 -> 9062.5478
A11: 43 | B11: 48.99 | C11: 0.065 | D11: =MIN((D7-D8-D9-D10),(B11-B10)) -> 0 | E11: =F2 -> 164345 | F11: =D11*E11*C11 -> 0
A12: 49 | C12: 0.055 | D12: =D7-(D8+D9+D10+D11) -> 0 | E12: =F2 -> 164345 | F12: =D12*E12*C12 -> 0
D13: =SUM(D8:D12) -> 35.586145 | F13: =SUM(F8:F12) -> 1179992.7
F18: =F13/L1 -> 0.14123422 | G18: Revenue Share

Sheet Asset Data_New Contract
A1: Month of Period Start | B1: Machine ID:SERIAL # | C1: Sum of Coin In | D1: Sum of Net Win | E1: Net Win_2 (Players Reward deducted) | F1: EGM Day Count | G1: WPUPD | H1: Fee/Revenue | I1: Upfront fee € | J1: Total Revenue | K1: Distinct Ser# Count | M1: Revenue Share | N1: ='Fee New Contract'!E13 -> 0.039998 | Q1: Total | R1: Per Machine
A2: 45962 | B2: EU0000700 | C2: 3912 | D2: 337.94 | E2: =D2-$R$2 -> 337.2727 | F2: 23 | G2: =D2/F2 -> 14.693043 | H2: =E2*$N$1 -> 13.490233 | I2: =$S$5 -> 61.15774 | J2: =H2+I2 -> 74.647973 | K2: 1 | P2: Players Reward scheme | Q2: 715.34946 | R2: =Q2/K1074 -> 0.6673036
A3: 45962 | B3: EU0000701 | C3: 3544 | D3: 474.57 | E3: =D3-$R$2 -> 473.9027 | F3: 15 | G3: =D3/F3 -> 31.638 | H3: =E3*$N$1 -> 18.95516 | I3: =$S$5 -> 61.15774 | J3: =H3+I3 -> 80.1129 | K3: 1
A4: 45962 | B4: EU0000703 | C4: 43203 | D4: 3664.62 | E4: =D4-$R$2 -> 3663.9527 | F4: 30 | G4: =D4/F4 -> 122.154 | H4: =E4*$N$1 -> 146.55078 | I4: =$S$5 -> 61.15774 | J4: =H4+I4 -> 207.70852 | K4: 1 | P4: Upfront fee $ | Q4: Exchange Rate | R4: Upfront fee € | S4: Upfront Fee per Machine
A5: 45962 | B5: EU0000706 | C5: 436442 | D5: 25829.99 | E5: =D5-$R$2 -> 25829.323 | F5: 1 | G5: =D5/F5 -> 25829.99 | H5: =E5*$N$1 -> 1033.1212 | I5: =$S$5 -> 61.15774 | J5: =H5+I5 -> 1094.279 | K5: 1 | P5: 66194 | Q5: 1.1087 | R5: 73389.288 | S5: 61.15774
A6: 45962 | B6: EU0000707 | C6: 8675 | D6: 96.36 | E6: =D6-$R$2 -> 95.692696 | F6: 30 | G6: =D6/F6 -> 3.212 | H6: =E6*$N$1 -> 3.8275165 | I6: =$S$5 -> 61.15774 | J6: =H6+I6 -> 64.985256 | K6: 1
A7: 45962 | B7: EU0000708 | C7: 27776 | D7: 336.98 | E7: =D7-$R$2 -> 336.3127 | F7: 30 | G7: =D7/F7 -> 11.232667 | H7: =E7*$N$1 -> 13.451835 | I7: =$S$5 -> 61.15774 | J7: =H7+I7 -> 74.609575 | K7: 1
A8: 45962 | B8: EU0000710 | C8: 938 | D8: 109.05 | E8: =D8-$R$2 -> 108.3827 | F8: 30 | G8: =D8/F8 -> 3.635 | H8: =E8*$N$1 -> 4.3350911 | I8: =$S$5 -> 61.15774 | J8: =H8+I8 -> 65.492831 | K8: 1
A9: 45962 | B9: EU0000718 | C9: 8643 | D9: 930.46 | E9: =D9-$R$2 -> 929.7927 | F9: 30 | G9: =D9/F9 -> 31.015333 | H9: =E9*$N$1 -> 37.189848 | I9: =$S$5 -> 61.15774 | J9: =H9+I9 -> 98.347588 | K9: 1
A10: 45962 | B10: EU0000724 | C10: 16196 | D10: 1583.68 | E10: =D10-$R$2 -> 1583.0127 | F10: 30 | G10: =D10/F10 -> 52.789333 | H10: =E10*$N$1 -> 63.317342 | I10: =$S$5 -> 61.15774 | J10: =H10+I10 -> 124.47508 | K10: 1
A11: 45962 | B11: EU0000726 | C11: 3822 | D11: -757.26 | E11: =D11-$R$2 -> -757.9273 | F11: 4 | G11: =D11/F11 -> -189.315 | H11: =E11*$N$1 -> -30.315576 | I11: =$S$5 -> 61.15774 | J11: =H11+I11 -> 30.842164 | K11: 1
A12: 45962 | B12: EU0000734 | C12: 6633 | D12: 489.84 | E12: =D12-$R$2 -> 489.1727 | F12: 30 | G12: =D12/F12 -> 16.328 | H12: =E12*$N$1 -> 19.56593 | I12: =$S$5 -> 61.15774 | J12: =H12+I12 -> 80.723669 | K12: 1
A13: 45962 | B13: EU0000738 | C13: 411 | D13: 58.8 | E13: =D13-$R$2 -> 58.132696 | F13: 11 | G13: =D13/F13 -> 5.3454545 | H13: =E13*$N$1 -> 2.3251916 | I13: =$S$5 -> 61.15774 | J13: =H13+I13 -> 63.482931 | K13: 1
A14: 45962 | B14: EU0000757 | C14: 7323 | D14: -953.59 | E14: =D14-$R$2 -> -954.2573 | F14: 30 | G14: =D14/F14 -> -31.786333 | H14: =E14*$N$1 -> -38.168384 | I14: =$S$5 -> 61.15774 | J14: =H14+I14 -> 22.989356 | K14: 1
A15: 45962 | B15: EU0000758 | C15: 35330 | D15: 3432.34 | E15: =D15-$R$2 -> 3431.6727 | F15: 24 | G15: =D15/F15 -> 143.01417 | H15: =E15*$N$1 -> 137.26004 | I15: =$S$5 -> 61.15774 | J15: =H15+I15 -> 198.41778 | K15: 1
A16: 45962 | B16: EU0000759 | C16: 966 | D16: 146.51 | E16: =D16-$R$2 -> 145.8427 | F16: 4 | G16: =D16/F16 -> 36.6275 | H16: =E16*$N$1 -> 5.8334162 | I16: =$S$5 -> 61.15774 | J16: =H16+I16 -> 66.991156 | K16: 1
A17: 45962 | B17: EU0000760 | C17: 4815 | D17: -97.57 | E17: =D17-$R$2 -> -98.237304 | F17: 30 | G17: =D17/F17 -> -3.2523333 | H17: =E17*$N$1 -> -3.9292957 | I17: =$S$5 -> 61.15774 | J17: =H17+I17 -> 57.228444 | K17: 1
... A61: 45962 | B61: EU0000809 | C61: 16723 | D61: 136.32 | E61: =D61-$R$2 -> 135.6527 | F61: 30 | G61: =D61/F61 -> 4.544 | H61: =E61*$N$1 -> 5.4258366 | I61: =$S$5 -> 61.15774 | J61: =H61+I61 -> 66.583576 | K61: 1
A62: 45962 | B62: EU0000810 | C62: 0 | E62: =D62-$R$2 -> -0.6673036 | F62: 2 | G62: =D62/F62 -> 0 | H62: =E62*$N$1 -> -0.026690809 | I62: =$S$5 -> 61.15774 | J62: =H62+I62 -> 61.131049 | K62: 1
A63: 45962 | B63: EU0000811 | C63: 18215 | D63: 835.53 | E63: =D63-$R$2 -> 834.8627 | F63: 30 | G63: =D63/F63 -> 27.851 | H63: =E63*$N$1 -> 33.392838 | I63: =$S$5 -> 61.15774 | J63: =H63+I63 -> 94.550578 | K63: 1
A64: 45962 | B64: EU0000812 | C64: 24344 | D64: 2184.39 | E64: =D64-$R$2 -> 2183.7227 | F64: 30 | G64: =D64/F64 -> 72.813 | H64: =E64*$N$1 -> 87.34454 | I64: =$S$5 -> 61.15774 | J64: =H64+I64 -> 148.50228 | K64: 1
A65: 45962 | B65: EU0000813 | C65: 287 | D65: 54.33 | E65: =D65-$R$2 -> 53.662696 | F65: 14 | G65: =D65/F65 -> 3.8807143 | H65: =E65*$N$1 -> 2.1464005 | I65: =$S$5 -> 61.15774 | J65: =H65+I65 -> 63.30414 | K65: 1
A66: 45962 | B66: EU0000814 | C66: 3899 | D66: -453.86 | E66: =D66-$R$2 -> -454.5273 | F66: 3 | G66: =D66/F66 -> -151.28667 | H66: =E66*$N$1 -> -18.180183 | I66: =$S$5 -> 61.15774 | J66: =H66+I66 -> 42.977557 | K66: 1
A67: 45962 | B67: EU0000815 | C67: 4036 | D67: 453.06 | E67: =D67-$R$2 -> 452.3927 | F67: 27 | G67: =D67/F67 -> 16.78 | H67: =E67*$N$1 -> 18.094803 | I67: =$S$5 -> 61.15774 | J67: =H67+I67 -> 79.252543 | K67: 1
A68: 45962 | B68: EU0000816 | C68: 9507 | D68: 534.95 | E68: =D68-$R$2 -> 534.2827 | F68: 30 | G68: =D68/F68 -> 17.831667 | H68: =E68*$N$1 -> 21.370239 | I68: =$S$5 -> 61.15774 | J68: =H68+I68 -> 82.527979 | K68: 1
A69: 45962 | B69: EU0000817 | C69: 8002 | D69: 317.31 | E69: =D69-$R$2 -> 316.6427 | F69: 30 | G69: =D69/F69 -> 10.577 | H69: =E69*$N$1 -> 12.665075 | I69: =$S$5 -> 61.15774 | J69: =H69+I69 -> 73.822814 | K69: 1
A70: 45962 | B70: EU0000818 | C70: 13872 | D70: 2339.44 | E70: =D70-$R$2 -> 2338.7727 | F70: 30 | G70: =D70/F70 -> 77.981333 | H70: =E70*$N$1 -> 93.54623 | I70: =$S$5 -> 61.15774 | J70: =H70+I70 -> 154.70397 | K70: 1
A71: 45962 | B71: EU0000820 | C71: 10910 | D71: 1762.05 | E71: =D71-$R$2 -> 1761.3827 | F71: 28 | G71: =D71/F71 -> 62.930357 | H71: =E71*$N$1 -> 70.451785 | I71: =$S$5 -> 61.15774 | J71: =H71+I71 -> 131.60952 | K71: 1
A72: 45962 | B72: EU0000822 | C72: 3645 | D72: -189.64 | E72: =D72-$R$2 -> -190.3073 | F72: 13 | G72: =D72/F72 -> -14.587692 | H72: =E72*$N$1 -> -7.6119115 | I72: =$S$5 -> 61.15774 | J72: =H72+I72 -> 53.545828 | K72: 1
A73: 45962 | B73: EU0000823 | C73: 25240 | D73: 1610.62 | E73: =D73-$R$2 -> 1609.9527 | F73: 30 | G73: =D73/F73 -> 53.687333 | H73: =E73*$N$1 -> 64.394888 | I73: =$S$5 -> 61.15774 | J73: =H73+I73 -> 125.55263 | K73: 1
A74: 45962 | B74: EU0000824 | C74: 9504 | D74: 932.54 | E74: =D74-$R$2 -> 931.8727 | F74: 30 | G74: =D74/F74 -> 31.084667 | H74: =E74*$N$1 -> 37.273044 | I74: =$S$5 -> 61.15774 | J74: =H74+I74 -> 98.430784 | K74: 1
... A78: 45962 | B78: EU0000829 | C78: 10084 | D78: 1757.16 | E78: =D78-$R$2 -> 1756.4927 | F78: 30 | G78: =D78/F78 -> 58.572 | H78: =E78*$N$1 -> 70.256195 | I78: =$S$5 -> 61.15774 | J78: =H78+I78 -> 131.41393 | K78: 1
A79: 45962 | B79: EU0000830 | C79: 0 | E79: =D79-$R$2 -> -0.6673036 | F79: 4 | G79: =D79/F79 -> 0 | H79: =E79*$N$1 -> -0.026690809 | I79: =$S$5 -> 61.15774 | J79: =H79+I79 -> 61.131049 | K79: 1
A80: 45962 | B80: EU0000831 | C80: 38875 | D80: 2328.86 | E80: =D80-$R$2 -> 2328.1927 | F80: 30 | G80: =D80/F80 -> 77.628667 | H80: =E80*$N$1 -> 93.123051 | I80: =$S$5 -> 61.15774 | J80: =H80+I80 -> 154.28079 | K80: 1
A81: 45962 | B81: EU0000832 | C81: 7714 | D81: 1008.6 | E81: =D81-$R$2 -> 1007.9327 | F81: 30 | G81: =D81/F81 -> 33.62 | H81: =E81*$N$1 -> 40.315292 | I81: =$S$5 -> 61.15774 | J81: =H81+I81 -> 101.47303 | K81: 1
A82: 45962 | B82: EU0000833 | C82: 215 | D82: 65 | E82: =D82-$R$2 -> 64.332696 | F82: 14 | G82: =D82/F82 -> 4.6428571 | H82: =E82*$N$1 -> 2.5731792 | I82: =$S$5 -> 61.15774 | J82: =H82+I82 -> 63.730919 | K82: 1
A83: 45962 | B83: EU0000834 | C83: 40249 | D83: 577.06 | E83: =D83-$R$2 -> 576.3927 | F83: 30 | G83: =D83/F83 -> 19.235333 | H83: =E83*$N$1 -> 23.054555 | I83: =$S$5 -> 61.15774 | J83: =H83+I83 -> 84.212295 | K83: 1
A84: 45962 | B84: EU0000835 | C84: 863 | D84: 26.83 | E84: =D84-$R$2 -> 26.162696 | F84: 5 | G84: =D84/F84 -> 5.366 | H84: =E84*$N$1 -> 1.0464555 | I84: =$S$5 -> 61.15774 | J84: =H84+I84 -> 62.204195 | K84: 1
A85: 45962 | B85: EU0000837 | C85: 212 | D85: 104.09 | E85: =D85-$R$2 -> 103.4227 | F85: 3 | G85: =D85/F85 -> 34.696667 | H85: =E85*$N$1 -> 4.136701 | I85: =$S$5 -> 61.15774 | J85: =H85+I85 -> 65.294441 | K85: 1
A86: 45962 | B86: EU0000838 | C86: 7474 | D86: 1107.75 | E86: =D86-$R$2 -> 1107.0827 | F86: 10 | G86: =D86/F86 -> 110.775 | H86: =E86*$N$1 -> 44.281094 | I86: =$S$5 -> 61.15774 | J86: =H86+I86 -> 105.43883 | K86: 1
A87: 45962 | B87: EU0000839 | C87: 19568 | D87: 663.34 | E87: =D87-$R$2 -> 662.6727 | F87: 30 | G87: =D87/F87 -> 22.111333 | H87: =E87*$N$1 -> 26.505583 | I87: =$S$5 -> 61.15774 | J87: =H87+I87 -> 87.663322 | K87: 1
A88: 45962 | B88: EU0000840 | C88: 21112 | D88: 1644.07 | E88: =D88-$R$2 -> 1643.4027 | F88: 14 | G88: =D88/F88 -> 117.43357 | H88: =E88*$N$1 -> 65.732821 | I88: =$S$5 -> 61.15774 | J88: =H88+I88 -> 126.89056 | K88: 1
A89: 45962 | B89: EU0000841 | C89: 5512 | D89: 679 | E89: =D89-$R$2 -> 678.3327 | F89: 30 | G89: =D89/F89 -> 22.633333 | H89: =E89*$N$1 -> 27.131951 | I89: =$S$5 -> 61.15774 | J89: =H89+I89 -> 88.289691 | K89: 1
A90: 45962 | B90: EU0000842 | C90: 36045 | D90: 4666.99 | E90: =D90-$R$2 -> 4666.3227 | F90: 30 | G90: =D90/F90 -> 155.56633 | H90: =E90*$N$1 -> 186.64358 | I90: =$S$5 -> 61.15774 | J90: =H90+I90 -> 247.80132 | K90: 1
A91: 45962 | B91: EU0000843 | C91: 1168 | D91: 111.05 | E91: =D91-$R$2 -> 110.3827 | F91: 30 | G91: =D91/F91 -> 3.7016667 | H91: =E91*$N$1 -> 4.4150871 | I91: =$S$5 -> 61.15774 | J91: =H91+I91 -> 65.572827 | K91: 1
... A129: 45962 | B129: EU0000887 | C129: 14768 | D129: 1899.46 | E129: =D129-$R$2 -> 1898.7927 | F129: 30 | G129: =D129/F129 -> 63.315333 | H129: =E129*$N$1 -> 75.94791 | I129: =$S$5 -> 61.15774 | J129: =H129+I129 -> 137.10565 | K129: 1
A130: 45962 | B130: EU0000888 | C130: 0 | E130: =D130-$R$2 -> -0.6673036 | F130: 10 | G130: =D130/F130 -> 0 | H130: =E130*$N$1 -> -0.026690809 | I130: =$S$5 -> 61.15774 | J130: =H130+I130 -> 61.131049 | K130: 1
A131: 45962 | B131: EU0000890 | C131: 60290 | D131: -2931.22 | E131: =D131-$R$2 -> -2931.8873 | F131: 30 | G131: =D131/F131 -> -97.707333 | H131: =E131*$N$1 -> -117.26963 | I131: =$S$5 -> 61.15774 | J131: =H131+I131 -> -56.111889 | K131: 1
A132: 45962 | B132: EU0000892 | C132: 3590 | D132: 787.36 | E132: =D132-$R$2 -> 786.6927 | F132: 20 | G132: =D132/F132 -> 39.368 | H132: =E132*$N$1 -> 31.466134 | I132: =$S$5 -> 61.15774 | J132: =H132+I132 -> 92.623874 | K132: 1
A133: 45962 | B133: EU0000893 | C133: 54203 | D133: 3426.23 | E133: =D133-$R$2 -> 3425.5627 | F133: 30 | G133: =D133/F133 -> 114.20767 | H133: =E133*$N$1 -> 137.01566 | I133: =$S$5 -> 61.15774 | J133: =H133+I133 -> 198.1734 | K133: 1
A134: 45962 | B134: EU0000894 | C134: 35652 | D134: 3842.81 | E134: =D134-$R$2 -> 3842.1427 | F134: 30 | G134: =D134/F134 -> 128.09367 | H134: =E134*$N$1 -> 153.67802 | I134: =$S$5 -> 61.15774 | J134: =H134+I134 -> 214.83576 | K134: 1
A135: 45962 | B135: EU0000896 | C135: 14454 | D135: 2891.32 | E135: =D135-$R$2 -> 2890.6527 | F135: 30 | G135: =D135/F135 -> 96.377333 | H135: =E135*$N$1 -> 115.62033 | I135: =$S$5 -> 61.15774 | J135: =H135+I135 -> 176.77807 | K135: 1
A136: 45962 | B136: EU0000898 | C136: 12382 | D136: -16.41 | E136: =D136-$R$2 -> -17.077304 | F136: 30 | G136: =D136/F136 -> -0.547 | H136: =E136*$N$1 -> -0.68305799 | I136: =$S$5 -> 61.15774 | J136: =H136+I136 -> 60.474682 | K136: 1
A137: 45962 | B137: EU0000899 | C137: 129 | D137: -78.89 | E137: =D137-$R$2 -> -79.557304 | F137: 6 | G137: =D137/F137 -> -13.148333 | H137: =E137*$N$1 -> -3.182133 | I137: =$S$5 -> 61.15774 | J137: =H137+I137 -> 57.975607 | K137: 1
A138: 45962 | B138: EU0000901 | C138: 235 | D138: -54.15 | E138: =D138-$R$2 -> -54.817304 | F138: 25 | G138: =D138/F138 -> -2.166 | H138: =E138*$N$1 -> -2.1925825 | I138: =$S$5 -> 61.15774 | J138: =H138+I138 -> 58.965157 | K138: 1
A139: 45962 | B139: EU0000902 | C139: 33 | D139: 14.95 | E139: =D139-$R$2 -> 14.282696 | F139: 2 | G139: =D139/F139 -> 7.475 | H139: =E139*$N$1 -> 0.57127929 | I139: =$S$5 -> 61.15774 | J139: =H139+I139 -> 61.729019 | K139: 1
A140: 45962 | B140: EU0000903 | C140: 19480 | D140: 2638.32 | E140: =D140-$R$2 -> 2637.6527 | F140: 30 | G140: =D140/F140 -> 87.944 | H140: =E140*$N$1 -> 105.50083 | I140: =$S$5 -> 61.15774 | J140: =H140+I140 -> 166.65857 | K140: 1
A141: 45962 | B141: EU0000904 | C141: 7818 | D141: 1418.93 | E141: =D141-$R$2 -> 1418.2627 | F141: 19 | G141: =D141/F141 -> 74.680526 | H141: =E141*$N$1 -> 56.727671 | I141: =$S$5 -> 61.15774 | J141: =H141+I141 -> 117.88541 | K141: 1
A142: 45962 | B142: EU0000905 | C142: 8412 | D142: 1514.4 | E142: =D142-$R$2 -> 1513.7327 | F142: 30 | G142: =D142/F142 -> 50.48 | H142: =E142*$N$1 -> 60.54628 | I142: =$S$5 -> 61.15774 | J142: =H142+I142 -> 121.70402 | K142: 1
... A260: 45962 | B260: MX0002421 | C260: 9416 | D260: -1125.14 | E260: =D260-$R$2 -> -1125.8073 | F260: 30 | G260: =D260/F260 -> -37.504667 | H260: =E260*$N$1 -> -45.030041 | I260: =$S$5 -> 61.15774 | J260: =H260+I260 -> 16.127699 | K260: 1
A261: 45962 | B261: MX0002422 | C261: 0 | E261: =D261-$R$2 -> -0.6673036 | F261: 5 | G261: =D261/F261 -> 0 | H261: =E261*$N$1 -> -0.026690809 | I261: =$S$5 -> 61.15774 | J261: =H261+I261 -> 61.131049 | K261: 1
A262: 45962 | B262: MX0002423 | C262: 1306 | D262: 332.38 | E262: =D262-$R$2 -> 331.7127 | F262: 5 | G262: =D262/F262 -> 66.476 | H262: =E262*$N$1 -> 13.267844 | I262: =$S$5 -> 61.15774 | J262: =H262+I262 -> 74.425584 | K262: 1
A263: 45962 | B263: MX0002424 | C263: 3229 | D263: 452.45 | E263: =D263-$R$2 -> 451.7827 | F263: 30 | G263: =D263/F263 -> 15.081667 | H263: =E263*$N$1 -> 18.070404 | I263: =$S$5 -> 61.15774 | J263: =H263+I263 -> 79.228144 | K263: 1
A264: 45962 | B264: MX0002425 | C264: 17132 | D264: 2078.13 | E264: =D264-$R$2 -> 2077.4627 | F264: 30 | G264: =D264/F264 -> 69.271 | H264: =E264*$N$1 -> 83.094353 | I264: =$S$5 -> 61.15774 | J264: =H264+I264 -> 144.25209 | K264: 1
A265: 45962 | B265: MX0002426 | C265: 24234 | D265: 1376.65 | E265: =D265-$R$2 -> 1375.9827 | F265: 30 | G265: =D265/F265 -> 45.888333 | H265: =E265*$N$1 -> 55.036556 | I265: =$S$5 -> 61.15774 | J265: =H265+I265 -> 116.1943 | K265: 1
A266: 45962 | B266: MX0002428 | C266: 11698 | D266: 1119.86 | E266: =D266-$R$2 -> 1119.1927 | F266: 30 | G266: =D266/F266 -> 37.328667 | H266: =E266*$N$1 -> 44.765469 | I266: =$S$5 -> 61.15774 | J266: =H266+I266 -> 105.92321 | K266: 1
A267: 45962 | B267: MX0002429 | C267: 15543 | D267: 569.02 | E267: =D267-$R$2 -> 568.3527 | F267: 30 | G267: =D267/F267 -> 18.967333 | H267: =E267*$N$1 -> 22.732971 | I267: =$S$5 -> 61.15774 | J267: =H267+I267 -> 83.890711 | K267: 1
A268: 45962 | B268: MX0002430 | C268: 5504 | D268: -47.34 | E268: =D268-$R$2 -> -48.007304 | F268: 30 | G268: =D268/F268 -> -1.578 | H268: =E268*$N$1 -> -1.9201961 | I268: =$S$5 -> 61.15774 | J268: =H268+I268 -> 59.237544 | K268: 1
A269: 45962 | B269: MX0002431 | C269: 3986 | D269: 500.58 | E269: =D269-$R$2 -> 499.9127 | F269: 30 | G269: =D269/F269 -> 16.686 | H269: =E269*$N$1 -> 19.995508 | I269: =$S$5 -> 61.15774 | J269: =H269+I269 -> 81.153248 | K269: 1
A270: 45962 | B270: MX0002432 | C270: 23373 | D270: 1504.14 | E270: =D270-$R$2 -> 1503.4727 | F270: 30 | G270: =D270/F270 -> 50.138 | H270: =E270*$N$1 -> 60.135901 | I270: =$S$5 -> 61.15774 | J270: =H270+I270 -> 121.29364 | K270: 1
A271: 45962 | B271: MX0002433 | C271: 2925 | D271: 421.46 | E271: =D271-$R$2 -> 420.7927 | F271: 25 | G271: =D271/F271 -> 16.8584 | H271: =E271*$N$1 -> 16.830866 | I271: =$S$5 -> 61.15774 | J271: =H271+I271 -> 77.988606 | K271: 1
A272: 45962 | B272: MX0002435 | C272: 44965 | D272: 2204.46 | E272: =D272-$R$2 -> 2203.7927 | F272: 30 | G272: =D272/F272 -> 73.482 | H272: =E272*$N$1 -> 88.1473 | I272: =$S$5 -> 61.15774 | J272: =H272+I272 -> 149.30504 | K272: 1
A273: 45962 | B273: MX0002437 | C273: 8097 | D273: 496.43 | E273: =D273-$R$2 -> 495.7627 | F273: 30 | G273: =D273/F273 -> 16.547667 | H273: =E273*$N$1 -> 19.829516 | I273: =$S$5 -> 61.15774 | J273: =H273+I273 -> 80.987256 | K273: 1
... A283: 45962 | B283: MX0002448 | C283: 18965 | D283: 1273.54 | E283: =D283-$R$2 -> 1272.8727 | F283: 30 | G283: =D283/F283 -> 42.451333 | H283: =E283*$N$1 -> 50.912362 | I283: =$S$5 -> 61.15774 | J283: =H283+I283 -> 112.0701 | K283: 1
A284: 45962 | B284: MX0002450 | C284: 0 | E284: =D284-$R$2 -> -0.6673036 | F284: 7 | G284: =D284/F284 -> 0 | H284: =E284*$N$1 -> -0.026690809 | I284: =$S$5 -> 61.15774 | J284: =H284+I284 -> 61.131049 | K284: 1
A285: 45962 | B285: MX0002451 | C285: 19627 | D285: 1966.54 | E285: =D285-$R$2 -> 1965.8727 | F285: 30 | G285: =D285/F285 -> 65.551333 | H285: =E285*$N$1 -> 78.630976 | I285: =$S$5 -> 61.15774 | J285: =H285+I285 -> 139.78872 | K285: 1
A286: 45962 | B286: MX0002454 | C286: 19947 | D286: 2146.95 | E286: =D286-$R$2 -> 2146.2827 | F286: 30 | G286: =D286/F286 -> 71.565 | H286: =E286*$N$1 -> 85.847015 | I286: =$S$5 -> 61.15774 | J286: =H286+I286 -> 147.00476 | K286: 1
A287: 45962 | B287: MX0002455 | C287: 40866 | D287: 2550.43 | E287: =D287-$R$2 -> 2549.7627 | F287: 30 | G287: =D287/F287 -> 85.014333 | H287: =E287*$N$1 -> 101.98541 | I287: =$S$5 -> 61.15774 | J287: =H287+I287 -> 163.14315 | K287: 1
A288: 45962 | B288: MX0002456 | C288: 1870 | D288: -404.3 | E288: =D288-$R$2 -> -404.9673 | F288: 21 | G288: =D288/F288 -> -19.252381 | H288: =E288*$N$1 -> -16.197882 | I288: =$S$5 -> 61.15774 | J288: =H288+I288 -> 44.959858 | K288: 1
A289: 45962 | B289: MX0002457 | C289: 8454 | D289: -580.61 | E289: =D289-$R$2 -> -581.2773 | F289: 30 | G289: =D289/F289 -> -19.353667 | H289: =E289*$N$1 -> -23.24993 | I289: =$S$5 -> 61.15774 | J289: =H289+I289 -> 37.90781 | K289: 1
A290: 45962 | B290: MX0002458 | C290: 16876 | D290: 3402.28 | E290: =D290-$R$2 -> 3401.6127 | F290: 30 | G290: =D290/F290 -> 113.40933 | H290: =E290*$N$1 -> 136.0577 | I290: =$S$5 -> 61.15774 | J290: =H290+I290 -> 197.21544 | K290: 1
A291: 45962 | B291: MX0002460 | C291: 23617 | D291: 257.69 | E291: =D291-$R$2 -> 257.0227 | F291: 30 | G291: =D291/F291 -> 8.5896667 | H291: =E291*$N$1 -> 10.280394 | I291: =$S$5 -> 61.15774 | J291: =H291+I291 -> 71.438134 | K291: 1
A292: 45962 | B292: MX0002985 | C292: 14974 | D292: 1651.04 | E292: =D292-$R$2 -> 1650.3727 | F292: 30 | G292: =D292/F292 -> 55.034667 | H292: =E292*$N$1 -> 66.011607 | I292: =$S$5 -> 61.15774 | J292: =H292+I292 -> 127.16935 | K292: 1
A293: 45962 | B293: MX0002986 | C293: 7420 | D293: -46.7 | E293: =D293-$R$2 -> -47.367304 | F293: 30 | G293: =D293/F293 -> -1.5566667 | H293: =E293*$N$1 -> -1.8945974 | I293: =$S$5 -> 61.15774 | J293: =H293+I293 -> 59.263142 | K293: 1
A294: 45962 | B294: MX0002987 | C294: 6769 | D294: 1918.74 | E294: =D294-$R$2 -> 1918.0727 | F294: 30 | G294: =D294/F294 -> 63.958 | H294: =E294*$N$1 -> 76.719072 | I294: =$S$5 -> 61.15774 | J294: =H294+I294 -> 137.87681 | K294: 1
A295: 45962 | B295: MX0002988 | C295: 23737 | D295: 2118.41 | E295: =D295-$R$2 -> 2117.7427 | F295: 30 | G295: =D295/F295 -> 70.613667 | H295: =E295*$N$1 -> 84.705472 | I295: =$S$5 -> 61.15774 | J295: =H295+I295 -> 145.86321 | K295: 1
A296: 45962 | B296: MX0002989 | C296: 5165 | D296: 377.63 | E296: =D296-$R$2 -> 376.9627 | F296: 30 | G296: =D296/F296 -> 12.587667 | H296: =E296*$N$1 -> 15.077754 | I296: =$S$5 -> 61.15774 | J296: =H296+I296 -> 76.235494 | K296: 1
... A333: 45962 | B333: MX0003031 | C333: 518 | D333: -20.54 | E333: =D333-$R$2 -> -21.207304 | F333: 30 | G333: =D333/F333 -> -0.68466667 | H333: =E333*$N$1 -> -0.84824973 | I333: =$S$5 -> 61.15774 | J333: =H333+I333 -> 60.30949 | K333: 1
A334: 45962 | B334: MX0003033 | C334: 0 | E334: =D334-$R$2 -> -0.6673036 | F334: 30 | G334: =D334/F334 -> 0 | H334: =E334*$N$1 -> -0.026690809 | I334: =$S$5 -> 61.15774 | J334: =H334+I334 -> 61.131049 | K334: 1
A335: 45962 | B335: MX0003034 | C335: 8552 | D335: 859.01 | E335: =D335-$R$2 -> 858.3427 | F335: 29 | G335: =D335/F335 -> 29.621034 | H335: =E335*$N$1 -> 34.331991 | I335: =$S$5 -> 61.15774 | J335: =H335+I335 -> 95.489731 | K335: 1
A336: 45962 | B336: MX0003035 | C336: 22153 | D336: 795.83 | E336: =D336-$R$2 -> 795.1627 | F336: 30 | G336: =D336/F336 -> 26.527667 | H336: =E336*$N$1 -> 31.804918 | I336: =$S$5 -> 61.15774 | J336: =H336+I336 -> 92.962657 | K336: 1
A337: 45962 | B337: MX0003036 | C337: 4145 | D337: -329.95 | E337: =D337-$R$2 -> -330.6173 | F337: 30 | G337: =D337/F337 -> -10.998333 | H337: =E337*$N$1 -> -13.224031 | I337: =$S$5 -> 61.15774 | J337: =H337+I337 -> 47.933709 | K337: 1
A338: 45962 | B338: MX0003037 | C338: 16906 | D338: 2408.4 | E338: =D338-$R$2 -> 2407.7327 | F338: 30 | G338: =D338/F338 -> 80.28 | H338: =E338*$N$1 -> 96.304492 | I338: =$S$5 -> 61.15774 | J338: =H338+I338 -> 157.46223 | K338: 1
A339: 45962 | B339: MX0003038 | C339: 3391 | D339: 380.7 | E339: =D339-$R$2 -> 380.0327 | F339: 30 | G339: =D339/F339 -> 12.69 | H339: =E339*$N$1 -> 15.200548 | I339: =$S$5 -> 61.15774 | J339: =H339+I339 -> 76.358288 | K339: 1
A340: 45962 | B340: MX0003039 | C340: 4291 | D340: 592.66 | E340: =D340-$R$2 -> 591.9927 | F340: 30 | G340: =D340/F340 -> 19.755333 | H340: =E340*$N$1 -> 23.678524 | I340: =$S$5 -> 61.15774 | J340: =H340+I340 -> 84.836264 | K340: 1
A341: 45962 | B341: MX0003040 | C341: 18051 | D341: 2565.13 | E341: =D341-$R$2 -> 2564.4627 | F341: 30 | G341: =D341/F341 -> 85.504333 | H341: =E341*$N$1 -> 102.57338 | I341: =$S$5 -> 61.15774 | J341: =H341+I341 -> 163.73112 | K341: 1
A342: 45962 | B342: MX0003041 | C342: 22754 | D342: 2052.88 | E342: =D342-$R$2 -> 2052.2127 | F342: 30 | G342: =D342/F342 -> 68.429333 | H342: =E342*$N$1 -> 82.084403 | I342: =$S$5 -> 61.15774 | J342: =H342+I342 -> 143.24214 | K342: 1
A343: 45962 | B343: MX0003043 | C343: 0 | E343: =D343-$R$2 -> -0.6673036 | F343: 22 | G343: =D343/F343 -> 0 | H343: =E343*$N$1 -> -0.026690809 | I343: =$S$5 -> 61.15774 | J343: =H343+I343 -> 61.131049 | K343: 1
A344: 45962 | B344: MX0003044 | C344: 0 | E344: =D344-$R$2 -> -0.6673036 | F344: 30 | G344: =D344/F344 -> 0 | H344: =E344*$N$1 -> -0.026690809 | I344: =$S$5 -> 61.15774 | J344: =H344+I344 -> 61.131049 | K344: 1
A345: 45962 | B345: MX0003045 | C345: 4268 | D345: -438.89 | E345: =D345-$R$2 -> -439.5573 | F345: 29 | G345: =D345/F345 -> -15.134138 | H345: =E345*$N$1 -> -17.581413 | I345: =$S$5 -> 61.15774 | J345: =H345+I345 -> 43.576327 | K345: 1
...

Sheet Fee New Contract
I2: VLT Days | J2: ='Asset Data_New Contract'!F1074 -> 29369
A3: OPERATING FEE CALCULATION | I3: GGR | J3: ='Asset Data_New Contract'!E1074 -> 1142398
A4: Scale | C4: % Commision | D4: Avr/NGR/month | E4: OP days | F4: Fee | I4: NGR | J4: =J3*70% -> 799678.61
D5: =J6 -> 27.228663 | I5: WPUPD | J5: =J3/J2 -> 38.898091
A6: 0 | B6: 28 | C6: 0.05714 | D6: =MIN(D5,B6) -> 27.228663 | E6: =J2 -> 29369 | F6: =D6*E6*C6 -> 45693.636 | I6: NWPUPD | J6: =J4/J2 -> 27.228663
A7: 28.01 | C7: 0.04286 | D7: =D5-D6 -> 0 | E7: =J2 -> 29369 | F7: =D7*E7*C7 -> 0
D8: =SUM(D6:D7) -> 27.228663 | F8: =SUM(F6:F7) -> 45693.636
D13: Revenue Share | E13: =F8/J3 -> 0.039998

Sheet OPAP's data_Initial Contract
A1: Serial No | B1: GGR | C1: GGR2 (Players Reward scheme deducted) | D1: Fee/Revenue | E1: Revenue Share | H1: Total | I1: Per Machine | K1: OPAP's Reporting Days
A2: MX0016251 | B2: 868.577 | C2: =B2-$I$2 -> 867.92771 | D2: =C2*$E$2 -> 123.58147 | E2: ='Fee Initial Contract OPAP D'!F18 -> 0.14238683 | G2: Players Reward scheme | H2: 3769.7781 | I2: =H2/5806 -> 0.64929006 | K2: 165227
A3: MX0017700 | B3: 657.263 | C3: =B3-$I$2 -> 656.61371 | D3: =C3*$E$2 -> 93.493143
A4: 2411994 | B4: 394.506 | C4: =B4-$I$2 -> 393.85671 | D4: =C4*$E$2 -> 56.080007
A5: EU0006954 | B5: -12.46 | C5: =B5-$I$2 -> -13.10929 | D5: =C5*$E$2 -> -1.8665902
A6: MX0010390 | B6: 388.007 | C6: =B6-$I$2 -> 387.35771 | D6: =C6*$E$2 -> 55.154635
A7: MX0010405 | B7: 353.377 | C7: =B7-$I$2 -> 352.72771 | D7: =C7*$E$2 -> 50.223779
A8: MX0016609 | B8: -1215.923 | C8: =B8-$I$2 -> -1216.5723 | D8: =C8*$E$2 -> -173.22387
A9: MX0018741 | B9: 1131.867 | C9: =B9-$I$2 -> 1131.2177 | D9: =C9*$E$2 -> 161.0705
A10: MX0016601 | B10: 1169.468 | C10: =B10-$I$2 -> 1168.8187 | D10: =C10*$E$2 -> 166.42439
A11: MX0017657 | B11: -49.864 | C11: =B11-$I$2 -> -50.51329 | D11: =C11*$E$2 -> -7.1924271
A12: MX0016606 | B12: 2017.874 | C12: =B12-$I$2 -> 2017.2247 | D12: =C12*$E$2 -> 287.22623
A13: 2411944 | B13: 232.082 | C13: =B13-$I$2 -> 231.43271 | D13: =C13*$E$2 -> 32.952969
A14: MX0007521 | B14: 33.532 | C14: =B14-$I$2 -> 32.88271 | D14: =C14*$E$2 -> 4.6820647
... A5807: MX0010389 | B5807: 1512.27 | C5807: =B5807-$I$2 -> 1511.6207 | D5807: =C5807*$E$2 -> 215.23488
B5808: =SUM(B2:B5807) -> 8278769.3 | C5808: =SUM(C2:C5807) -> 8274999.5 | D5808: =SUM(D2:D5807) -> 1178250.9

Sheet Fee Initial Contract OPAP D
A1: Sum of Daily NGR of all VLTs for a month period (invoice period): | F1: =L1*0.7 -> 5792499.7 | K1: GGR | L1: ='OPAP''s data_Initial Contract'!C5808 -> 8274999.5
A2: Sum of operational days (reported days) of all VLTs for a month period: | F2: ='OPAP''s data_Initial Contract'!K2 -> 165227 | K2: WPUPD | L2: =F3/0.7 -> 50.082611
A3: Average NGR per day per VLT for a month period : | F3: =F1/F2 -> 35.057828 | G3: NWPUPD
A5: OPERATING FEE CALCULATION
A6: Scale | C6: % Commision | D6: Avr/NGR/month | E6: OP days | F6: Fee
D7: =F3 -> 35.057828
A8: 0 | B8: 28.99 | C8: 0.217 | D8: =MIN(D7,B8) -> 28.99 | E8: =F2 -> 165227 | F8: =D8*E8*C8 -> 1039415
A9: 29 | B9: 34.99 | C9: 0.139 | D9: =MIN((D7-D8),(B9-B8)) -> 6 | E9: =F2 -> 165227 | F9: =D9*E9*C9 -> 137799.32
A10: 35 | B10: 42.99 | C10: 0.0925 | D10: =MIN((D7-D8-D9),(B10-B9)) -> 0.067827612 | E10: =F2 -> 165227 | F10: =D10*E10*C10 -> 1036.6431
A11: 43 | B11: 48.99 | C11: 0.065 | D11: =MIN((D7-D8-D9-D10),(B11-B10)) -> 0 | E11: =F2 -> 165227 | F11: =D11*E11*C11 -> 0
A12: 49 | C12: 0.055 | D12: =D7-(D8+D9+D10+D11) -> 0 | E12: =F2 -> 165227 | F12: =D12*E12*C12 -> 0
D13: =SUM(D8:D12) -> 35.057828 | F13: =SUM(F8:F12) -> 1178250.9
F18: =F13/L1 -> 0.14238683 | G18: Revenue Share

Sheet OPAP's data_New Contract
A1: Serial No | B1: GGR | C1: GGR2 (Players Reward scheme deducted) | D1: Fee/Revenue | E1: Upfront Fee | F1: Total Revenue | G1: Revenue Share | J1: Total | K1: Per Machine | N1: OPAP's Reporting Days
A2: MX0004893 | B2: -810.188 | C2: =B2-$K$2 -> -810.84489 | D2: =C2*$G$2 -> -32.433877 | E2: =$L$5 -> 61.15774 | F2: =D2+E2 -> 28.723863 | G2: ='Fee New Contract OPAP Data'!E13 -> 0.0400001 | I2: Players Reward scheme | J2: 715.34946 | K2: =J2/1089 -> 0.65688656 | N2: 29721
A3: EU0000912 | B3: -369.423 | C3: =B3-$K$2 -> -370.07989 | D3: =C3*$G$2 -> -14.803232 | E3: =$L$5 -> 61.15774 | F3: =D3+E3 -> 46.354507
A4: MX0003067 | B4: 689.254 | C4: =B4-$K$2 -> 688.59711 | D4: =C4*$G$2 -> 27.543953 | E4: =$L$5 -> 61.15774 | F4: =D4+E4 -> 88.701693 | I4: Upfront fee $ | J4: Exchange Rate | K4: Upfront fee € | L4: Upfront Fee per Machine
A5: EU0000803 | B5: 2109.543 | C5: =B5-$K$2 -> 2108.8861 | D5: =C5*$G$2 -> 84.355655 | E5: =$L$5 -> 61.15774 | F5: =D5+E5 -> 145.5134 | I5: 66194 | J5: 1.1087 | K5: =I5*J5 -> 73389.288 | L5: =K5/1200 -> 61.15774
A6: MX0002418 | B6: 143.221 | C6: =B6-$K$2 -> 142.56411 | D6: =C6*$G$2 -> 5.7025788 | E6: =$L$5 -> 61.15774 | F6: =D6+E6 -> 66.860319
A7: MX0002433 | B7: 553.655 | C7: =B7-$K$2 -> 552.99811 | D7: =C7*$G$2 -> 22.11998 | E7: =$L$5 -> 61.15774 | F7: =D7+E7 -> 83.27772
A8: MX0004021 | B8: 91.813 | C8: =B8-$K$2 -> 91.156113 | D8: =C8*$G$2 -> 3.6462537 | E8: =$L$5 -> 61.15774 | F8: =D8+E8 -> 64.803993
A9: MX0003001 | B9: -681.752 | C9: =B9-$K$2 -> -682.40889 | D9: =C9*$G$2 -> -27.296424 | E9: =$L$5 -> 61.15774 | F9: =D9+E9 -> 33.861316
A10: MX0004300 | B10: -300.184 | C10: =B10-$K$2 -> -300.84089 | D10: =C10*$G$2 -> -12.033666 | E10: =$L$5 -> 61.15774 | F10: =D10+E10 -> 49.124074
A11: MX0004841 | B11: 805.202 | C11: =B11-$K$2 -> 804.54511 | D11: =C11*$G$2 -> 32.181885 | E11: =$L$5 -> 61.15774 | F11: =D11+E11 -> 93.339625
A12: MX0004901 | B12: 970.04 | C12: =B12-$K$2 -> 969.38311 | D12: =C12*$G$2 -> 38.775421 | E12: =$L$5 -> 61.15774 | F12: =D12+E12 -> 99.933161
A13: MX0004976 | B13: 12.005 | C13: =B13-$K$2 -> 11.348113 | D13: =C13*$G$2 -> 0.45392567 | E13: =$L$5 -> 61.15774 | F13: =D13+E13 -> 61.611666
A14: MX0003929 | B14: -187.165 | C14: =B14-$K$2 -> -187.82189 | D14: =C14*$G$2 -> -7.5128942 | E14: =$L$5 -> 61.15774 | F14: =D14+E14 -> 53.644846
A15: MX0004977 | B15: 118.937 | C15: =B15-$K$2 -> 118.28011 | D15: =C15*$G$2 -> 4.7312164 | E15: =$L$5 -> 61.15774 | F15: =D15+E15 -> 65.888956
A16: MX0002358 | B16: 301.183 | C16: =B16-$K$2 -> 300.52611 | D16: =C16*$G$2 -> 12.021075 | E16: =$L$5 -> 61.15774 | F16: =D16+E16 -> 73.178814
A17: MX0004028 | B17: -95.048 | C17: =B17-$K$2 -> -95.704887 | D17: =C17*$G$2 -> -3.828205 | E17: =$L$5 -> 61.15774 | F17: =D17+E17 -> 57.329535
... A1090: MX0003658 | B1090: -1082.582 | C1090: =B1090-$K$2 -> -1083.2389 | D1090: =C1090*$G$2 -> -43.329664 | E1090: =$L$5 -> 61.15774 | F1090: =D1090+E1090 -> 17.828076
B1091: =SUM(B2:B1090) -> 1113917.5 | C1091: =SUM(C2:C1090) -> 1113202.2 | D1091: =SUM(D2:D1090) -> 44528.198 | E1091: =SUM(E2:E1090) -> 66600.779 | F1091: =SUM(F2:F1090) -> 111128.98

Sheet Fee New Contract OPAP Data
I2: VLT Days | J2: ='OPAP''s data_New Contract'!N2 -> 29721
A3: OPERATING FEE CALCULATION | I3: GGR | J3: ='OPAP''s data_New Contract'!C1091 -> 1113202.2
A4: Scale | C4: % Commision | D4: Avr/NGR/month | E4: OP days | F4: Fee | I4: NGR | J4: =J3*70% -> 779241.51
D5: =J6 -> 26.218549 | I5: WPUPD | J5: =J3/J2 -> 37.455071
A6: 0 | B6: 28 | C6: 0.057143 | D6: =MIN(D5,B6) -> 26.218549 | E6: =J2 -> 29721 | F6: =D6*E6*C6 -> 44528.198 | I6: NWPUPD | J6: =J4/J2 -> 26.218549
A7: 28.01 | C7: 0.04286 | D7: =D5-D6 -> 0 | E7: =J2 -> 29721 | F7: =D7*E7*C7 -> 0
D8: =SUM(D6:D7) -> 26.218549 | F8: =SUM(F6:F7) -> 44528.198
D13: Revenue Share | E13: =F8/J3 -> 0.0400001
